wxutils/__init__.py
wxutils/buttons.py
wxutils/choice.py
wxutils/colors.py
wxutils/dates.py
wxutils/dialogs.py
wxutils/filechecklist.py
wxutils/floats.py
wxutils/gridpanel.py
wxutils/icons.py
wxutils/listbox.py
wxutils/myfloatspin.py
wxutils/notebooks.py
wxutils/passwords.py
wxutils/paths.py
wxutils/periodictable.py
wxutils/readlinetextctrl.py
wxutils/text.py
wxutils/utils.py
wxutils/version.py
wxutils-0.3.6.dist-info/licenses/LICENSE
wxutils-0.3.6.dist-info/METADATA
wxutils-0.3.6.dist-info/WHEEL
wxutils-0.3.6.dist-info/top_level.txt
wxutils-0.3.6.dist-info/RECORD
