Metadata-Version: 2.4
Name: wxutils
Version: 0.3.6
Summary: utilities and conveniences for wxPython
Author-email: Matthew Newville <matt.newville@gmail.com>
License-Expression: MIT
Project-URL: Homepage, https://github.com/newville/wxutils
Project-URL: Documentation, https://github.com/newville/wxutils
Project-URL: Tracker, https://github.com/newville/wxutils/issues
Keywords: wxPython
Classifier: Development Status :: 5 - Production/Stable
Classifier: Intended Audience :: End Users/Desktop
Classifier: Intended Audience :: Developers
Classifier: Operating System :: MacOS :: MacOS X
Classifier: Operating System :: Microsoft :: Windows
Classifier: Operating System :: POSIX
Classifier: Programming Language :: Python
Classifier: Programming Language :: Python :: 3 :: Only
Classifier: Programming Language :: Python :: 3.9
Classifier: Programming Language :: Python :: 3.10
Classifier: Programming Language :: Python :: 3.11
Classifier: Programming Language :: Python :: 3.12
Classifier: Programming Language :: Python :: 3.13
Requires-Python: >=3.9
License-File: LICENSE
Requires-Dist: wxPython>=4.1.0
Provides-Extra: dev
Requires-Dist: build; extra == "dev"
Requires-Dist: twine; extra == "dev"
Provides-Extra: doc
Requires-Dist: Sphinx; extra == "doc"
Provides-Extra: test
Requires-Dist: pytest; extra == "test"
Requires-Dist: pytest-cov; extra == "test"
Requires-Dist: coverage; extra == "test"
Provides-Extra: all
Requires-Dist: wxutils[dev,doc,test]; extra == "all"
Dynamic: license-file
